{
  "_class": "shapeGroup",
  "clippingMaskMode": 0,
  "do_objectID": "45C6A428-9AF5-4DA4-B7B5-CB28C120D519",
  "exportOptions": {
    "_class": "exportOptions",
    "do_objectID": "31D2FE0F-9C75-4D0B-B5A5-2B7151D08AA3",
    "exportFormats": [
    ],
    "includedLayerIds": [
    ],
    "layerOptions": 0,
    "shouldTrim": false
  },
  "frame": {
    "_class": "rect",
    "constrainProportions": false,
    "do_objectID": "4741F9E2-7DC4-4A00-9A14-A06F52EC484C",
    "height": 65,
    "width": 251,
    "x": 0,
    "y": 0
  },
  "hasClickThrough": false,
  "hasClippingMask": false,
  "isFlippedHorizontal": false,
  "isFlippedVertical": false,
  "isLocked": false,
  "isVisible": true,
  "layerListExpandedType": 1,
  "layers": [
    {
      "class": "rectangle",
      "id": "E55F8837-BAE6-4F32-8577-54BBD2225202"
    }
  ],
  "name": "Mask Copy",
  "nameIsFixed": false,
  "resizingConstraint": 63,
  "resizingType": 0,
  "rotation": 0,
  "shouldBreakMaskChain": false,
  "style": {
    "_class": "style",
    "borders": [
      {
        "_class": "border",
        "color": {
          "_class": "color",
          "alpha": 1,
          "blue": 0.592,
          "green": 0.592,
          "red": 0.592
        },
        "fillType": 0,
        "isEnabled": false,
        "position": 1,
        "thickness": 1
      }
    ],
    "contextSettings": {
      "_class": "graphicsContextSettings",
      "blendMode": 0,
      "do_objectID": "69AC47DC-7C4A-484F-AF6D-9E4E30D674B0",
      "opacity": 0.1957653985507246
    },
    "do_objectID": "46109ECA-C5C0-4F89-8AE5-481C0C2B0593",
    "endDecorationType": 0,
    "fills": [
      {
        "_class": "fill",
        "color": {
          "_class": "color",
          "alpha": 1,
          "blue": 0.847,
          "green": 0.847,
          "red": 0.847
        },
        "fillType": 0,
        "isEnabled": false,
        "noiseIndex": 0,
        "noiseIntensity": 0,
        "patternFillType": 1,
        "patternTileScale": 1
      }
    ],
    "miterLimit": 10,
    "startDecorationType": 0
  },
  "windingRule": 1
}