{
  "_class": "text",
  "attributedString": {
    "_class": "attributedString",
    "attributes": [
      {
        "_class": "stringAttribute",
        "attributes": {
          "MSAttributedStringColorAttribute": {
            "_class": "color",
            "alpha": 1,
            "blue": 0.223984906462585,
            "green": 0.1823391826798163,
            "red": 0.1807150949868584
          },
          "MSAttributedStringFontAttribute": {
            "_class": "fontDescriptor",
            "attributes": {
              "name": "SFUIText-Semibold",
              "size": 32
            }
          },
          "kerning": -0.4517647,
          "paragraphStyle": {
            "_class": "paragraphStyle",
            "alignment": 2
          }
        },
        "length": 2,
        "location": 0
      }
    ],
    "string": "23"
  },
  "automaticallyDrawOnUnderlyingPath": false,
  "do_objectID": "6A44B1DB-CE88-4EA4-BBB9-99AB048A418E",
  "dontSynchroniseWithSymbol": false,
  "exportOptions": {
    "_class": "exportOptions",
    "do_objectID": "FFA8F2B4-AF08-403F-80F2-8D91EBF81539",
    "exportFormats": [
    ],
    "includedLayerIds": [
    ],
    "layerOptions": 0,
    "shouldTrim": false
  },
  "frame": {
    "_class": "rect",
    "constrainProportions": false,
    "do_objectID": "E927D883-8B54-47F6-AB47-74E9683C6FCB",
    "height": 38,
    "width": 65,
    "x": 0,
    "y": 0
  },
  "glyphBounds": "{{14, 6}, {38, 25}}",
  "isFlippedHorizontal": false,
  "isFlippedVertical": false,
  "isLocked": false,
  "isVisible": true,
  "layerListExpandedType": 0,
  "lineSpacingBehaviour": 2,
  "name": "23",
  "nameIsFixed": false,
  "resizingConstraint": 47,
  "resizingType": 0,
  "rotation": 0,
  "shouldBreakMaskChain": false,
  "style": {
    "_class": "style",
    "do_objectID": "CB7132F1-C9AB-43E7-80FA-79C4F6236E71",
    "endDecorationType": 0,
    "miterLimit": 10,
    "startDecorationType": 0,
    "textStyle": {
      "_class": "textStyle",
      "do_objectID": "11551F24-B8C8-48C9-A194-F81EB4A58099",
      "encodedAttributes": {
        "MSAttributedStringColorAttribute": {
          "_class": "color",
          "alpha": 1,
          "blue": 0.223984906462585,
          "green": 0.1823391826798163,
          "red": 0.1807150949868584
        },
        "MSAttributedStringFontAttribute": {
          "_class": "fontDescriptor",
          "attributes": {
            "name": "SFUIText-Semibold",
            "size": 32
          }
        },
        "kerning": -0.4517647,
        "paragraphStyle": {
          "_class": "paragraphStyle",
          "alignment": 2
        }
      },
      "verticalAlignment": 0
    }
  },
  "textBehaviour": 1
}