{
  "_class": "group",
  "do_objectID": "47CEEA3D-CC6D-4F0D-9BBC-C1C09F25A5B3",
  "exportOptions": {
    "_class": "exportOptions",
    "do_objectID": "ABABA96A-A33F-4C1B-A71F-BE1888ACA053",
    "exportFormats": [
    ],
    "includedLayerIds": [
    ],
    "layerOptions": 0,
    "shouldTrim": false
  },
  "frame": {
    "_class": "rect",
    "constrainProportions": false,
    "do_objectID": "6E329E44-D5F0-4271-A050-C59AF930BAA0",
    "height": 975,
    "width": 682,
    "x": 69,
    "y": 21
  },
  "hasClickThrough": false,
  "isFlippedHorizontal": false,
  "isFlippedVertical": false,
  "isLocked": false,
  "isVisible": true,
  "layerListExpandedType": 2,
  "layers": [
    {
      "class": "shapeGroup",
      "id": "5E414A42-668C-49C5-9743-F77B3CB688A1"
    },
    {
      "class": "shapeGroup",
      "id": "96A400AA-B7DC-41AF-B3D2-F639ACD3F29D"
    },
    {
      "class": "shapeGroup",
      "id": "74E84B40-8CAE-49DA-BDF6-9A8562CB3E5E"
    },
    {
      "class": "shapeGroup",
      "id": "9CFC9D1C-CE4B-4102-87D6-664098DC3734"
    },
    {
      "class": "shapeGroup",
      "id": "2909EE15-628C-43D1-9BCB-E05CD39DBB6B"
    },
    {
      "class": "shapeGroup",
      "id": "1CD146C5-88B1-4383-87E1-B3B59492C98C"
    },
    {
      "class": "shapeGroup",
      "id": "D7F833BA-9525-4A34-AC2B-56DBDA4D3CC8"
    },
    {
      "class": "shapeGroup",
      "id": "3072BF25-79F6-4479-8766-CC63BC6EF47A"
    },
    {
      "class": "shapeGroup",
      "id": "9CEA6F92-DBAA-4B93-B2FE-087A70A3154F"
    },
    {
      "class": "shapeGroup",
      "id": "A2DDC105-5239-4A36-B04D-8BF648AD5FC0"
    }
  ],
  "name": "Lines Calendar",
  "nameIsFixed": true,
  "resizingConstraint": 63,
  "resizingType": 0,
  "rotation": 0,
  "shouldBreakMaskChain": false,
  "style": {
    "_class": "style",
    "do_objectID": "73D17AC5-105B-487C-8CB8-79614DBA6462",
    "endDecorationType": 0,
    "miterLimit": 10,
    "startDecorationType": 0
  }
}