{
  "_class": "shapePath",
  "booleanOperation": -1,
  "do_objectID": "E248BBC5-5052-468F-A42A-4284FA585B65",
  "edited": true,
  "exportOptions": {
    "_class": "exportOptions",
    "do_objectID": "D106C3E0-8E74-4A4E-BDEF-58204BEFF8ED",
    "exportFormats": [
    ],
    "includedLayerIds": [
    ],
    "layerOptions": 0,
    "shouldTrim": false
  },
  "frame": {
    "_class": "rect",
    "constrainProportions": false,
    "do_objectID": "FD7A9DD6-9142-4ED0-B843-8B6BE3255FC2",
    "height": 18.82000000000005,
    "width": 15.21000000000004,
    "x": 2.90199999999993,
    "y": 2.536000000000002
  },
  "isClosed": false,
  "isFlippedHorizontal": false,
  "isFlippedVertical": false,
  "isLocked": false,
  "isVisible": true,
  "layerListExpandedType": 0,
  "name": "Path",
  "nameIsFixed": false,
  "pointRadiusBehaviour": 1,
  "points": [
    {
      "_class": "curvePoint",
      "cornerRadius": 0,
      "curveFrom": "{1, 0.18831030818278588}",
      "curveMode": 4,
      "curveTo": "{1, 0.5}",
      "hasCurveFrom": true,
      "hasCurveTo": false,
      "point": "{1, 0.5}"
    },
    {
      "_class": "curvePoint",
      "cornerRadius": 0,
      "curveFrom": "{0.18645627876397147, 0}",
      "curveMode": 2,
      "curveTo": "{0.81354372123602858, 0}",
      "hasCurveFrom": true,
      "hasCurveTo": true,
      "point": "{0.49993425378040918, 0}"
    },
    {
      "_class": "curvePoint",
      "cornerRadius": 0,
      "curveFrom": "{0, 0.81168969181721418}",
      "curveMode": 2,
      "curveTo": "{0, 0.18831030818278588}",
      "hasCurveFrom": true,
      "hasCurveTo": true,
      "point": "{0, 0.5}"
    },
    {
      "_class": "curvePoint",
      "cornerRadius": 0,
      "curveFrom": "{0.81354372123602858, 1}",
      "curveMode": 2,
      "curveTo": "{0.18645627876397147, 1}",
      "hasCurveFrom": true,
      "hasCurveTo": true,
      "point": "{0.49993425378040918, 1}"
    },
    {
      "_class": "curvePoint",
      "cornerRadius": 0,
      "curveFrom": "{1, 0.5}",
      "curveMode": 4,
      "curveTo": "{1, 0.81168969181721418}",
      "hasCurveFrom": false,
      "hasCurveTo": true,
      "point": "{1, 0.5}"
    }
  ],
  "resizingConstraint": 63,
  "resizingType": 0,
  "rotation": 0,
  "shouldBreakMaskChain": false
}